LICENSE
README.md
setup.cfg
setup.py
lmqg/__init__.py
lmqg/automatic_evaluation.py
lmqg/data.py
lmqg/exceptions.py
lmqg/grid_searcher.py
lmqg/inference_api.py
lmqg/language_model.py
lmqg/spacy_module.py
lmqg/trainer.py
lmqg.egg-info/PKG-INFO
lmqg.egg-info/SOURCES.txt
lmqg.egg-info/dependency_links.txt
lmqg.egg-info/entry_points.txt
lmqg.egg-info/requires.txt
lmqg.egg-info/top_level.txt
lmqg/automatic_evaluation_tool/__init__.py
lmqg/automatic_evaluation_tool/bertscore.py
lmqg/automatic_evaluation_tool/meteor.py
lmqg/automatic_evaluation_tool/moverscore.py
lmqg/automatic_evaluation_tool/qa_aligned_f1_score.py
lmqg/automatic_evaluation_tool/rouge.py
lmqg/automatic_evaluation_tool/text_normalization.py
lmqg/automatic_evaluation_tool/bert_score/__init__.py
lmqg/automatic_evaluation_tool/bert_score/score.py
lmqg/automatic_evaluation_tool/bert_score/scorer.py
lmqg/automatic_evaluation_tool/bert_score/utils.py
lmqg/automatic_evaluation_tool/bleu/__init__.py
lmqg/automatic_evaluation_tool/bleu/bleu.py
lmqg/automatic_evaluation_tool/bleu/bleu_scorer.py
lmqg/automatic_evaluation_tool/meteor/__init__.py
lmqg/automatic_evaluation_tool/meteor/meteor.py
lmqg/lmqg_cl/__init__.py
lmqg/lmqg_cl/model_evaluation.py
lmqg/lmqg_cl/model_evaluation_qa.py
lmqg/lmqg_cl/model_evaluation_qa_based_metric.py
lmqg/lmqg_cl/model_evaluation_qag.py
lmqg/lmqg_cl/model_finetuning.py
lmqg/lmqg_cl/push_to_hf.py
lmqg/lmqg_cl/readme_template.py
lmqg/qa_evaluation_tool/__init__.py
lmqg/qa_evaluation_tool/generate_pseudo_qa_data.py
lmqg/qa_evaluation_tool/run_qa.py
lmqg/qa_evaluation_tool/trainer_qa.py
lmqg/qa_evaluation_tool/utils_qa.py